[
    {
        "name": "Crater",
        "chest_unopened_img": "images/items/databox_close.png",
		"overlay_background": "#000000",
        "chest_opened_img": "images/items/databox_open.png",
        "color": "#FFFFFF",
        "children": 
        [
            {
                "name": "Blood Kelp Trench Wreck \n (x: -1208, y: -332, z: -390)",
                "map_locations": 
                [
                    {
                        "map": "Crater",
                        "x": 175,
                        "y": 491
                    }
                ],
                "sections": 
                [
                    {
                        "name": "Databox Outside",
                        "access_rules": 
                        [
                            "seaglide:2, rebreather",
                            "hightank, fins, rebreather, modify:3",
                            "vehiclebay:3, seamoth:3, rebreather",
                            "vehiclebay:3, prawn:4",
                            "vehiclebay:3, cyclops:9"
                        ],
                        "item_count": 1
                    },
                    {
                        "name": "Databox Inside",
                        "access_rules": 
                        [
                            "seaglide:2, rebreather",
                            "hightank, fins, rebreather, modify:3",
                            "vehiclebay:3, seamoth:3, rebreather",
                            "vehiclebay:3, prawn:4",
                            "vehiclebay:3, cyclops:9"
                        ],
                        "item_count": 1
                    },
                    {
                        "name": "PDA",
                        "access_rules": 
                        [
                            "seaglide:2, rebreather",
                            "hightank, fins, rebreather, modify:3",
                            "vehiclebay:3, seamoth:3, rebreather",
                            "vehiclebay:3, prawn:4",
                            "vehiclebay:3, cyclops:9"
                        ],
                        "item_count": 1
                    }
                ]
            },
            {
                "name": "Bulb Zone West Wreck \n (x: 903, y: -220, z: 590)",
                "map_locations": 
                [
                    {
                        "map": "Crater",
                        "x": 654,
                        "y": 260
                    }
                ],
                "sections": 
                [
                    {
                        "name": "Outside Databox",
                        "access_rules": 
                        [
                            "radsuit,rebreather"
                        ],
                        "item_count": 1
                    },
                    {
                        "name": "Under Databox",
                        "access_rules": 
                        [
                            "radsuit,rebreather"
                        ],  
                        "item_count": 1
                    },
                    {
                        "name": "Inside Databox",
                        "access_rules": 
                        [
                            "cutter:3,rebreather,radsuit"
                        ],
                        "item_count": 1
                    },
                    {
                        "name": "PDA",
                        "access_rules": 
                        [
                            "cutter:3,rebreather,radsuit"
                        ],
                        "item_count": 1
                    }
                ]
            },
            {
                "name": "Bulb Zone Lifepod 12 \n (x: 1120, y: -265, z: 560)",
                "map_locations": 
                [
                    {
                        "map": "Crater",
                        "x": 692,
                        "y": 278
                    }
                ],
                "sections": 
                [       
                    {
                        "name": "Databox",
                        "access_rules": 
                        [
                            "seaglide:2, rebreather, radsuit",
                            "hightank, fins, rebreather, modify:3, radsuit",
                            "vehiclebay:3, seamoth:3, rebreather,radsuit",
                            "vehiclebay:3, prawn:4,radsuit",
                            "vehiclebay:3, cyclops:9,radsuit"
                        ],
                        "item_count": 1
                    },
                    {
                        "name": "PDA",
                        "access_rules": 
                        [
                            "seaglide:2, rebreather, radsuit",
                            "hightank, fins, rebreather, modify:3, radsuit",
                            "vehiclebay:3, seamoth:3, rebreather",
                            "vehiclebay:3, prawn:4",
                            "vehiclebay:3, cyclops:9"
                        ],
                        "item_count": 1
                    }
                ]
            },
            {
                "name": "Bulb Zone Wreck East \n (x: 1292, y: -200, z: 583)",
                "map_locations": 
                [
                    {
                        "map": "Crater",
                        "x": 720,
                        "y": 266
                    }
                ],
                "sections": 
                [       
                    {
                        "name": "Databox",
                        "access_rules": 
                        [
                            "rebreather"
                        ],
                        "item_count": 1
                    }
                ]
            },
            {
                "name": "Dunes North Wreck \n (x: -1407, y: -344, z: 721)",
                "map_locations": 
                [
                    {
                        "map": "Crater",
                        "x": 115,
                        "y": 235
                    }
                ],
                "sections": 
                [
                    {
                        "name": "Outside Databox",
                        "access_rules": 
                        [
                            "seaglide:2, rebreather",
                            "hightank, fins, rebreather, modify:3",
                            "vehiclebay:3, seamoth:3, rebreather",
                            "vehiclebay:3, prawn:4",
                            "vehiclebay:3, cyclops:9"
                        ],
                        "item_count": 1
                    },
                    {
                        "name": "Office Databox",
                        "access_rules": 
                        [
                            "seaglide:2, rebreather",
                            "hightank, fins, rebreather, modify:3",
                            "vehiclebay:3, seamoth:3, rebreather",
                            "vehiclebay:3, prawn:4",
                            "vehiclebay:3, cyclops:9"
                        ],
                        "item_count": 1
                    },
                    {
                        "name": "PDA",
                        "access_rules": 
                        [
                            "seaglide:2, rebreather",
                            "hightank, fins, rebreather, modify:3",
                            "vehiclebay:3, seamoth:3, rebreather",
                            "vehiclebay:3, prawn:4",
                            "vehiclebay:3, cyclops:9"
                        ],
                        "item_count": 1
                    },
                    {
                        "name": "Cargo Databox",
                        "access_rules": 
                        [
                            "seaglide:2, rebreather, cutter:3",
                            "hightank, fins, rebreather, modify:3, cutter:3",
                            "vehiclebay:3, seamoth:3, rebreather, cutter:3",
                            "vehiclebay:3, prawn:4, cutter:3",
                            "vehiclebay:3, cyclops:9, cutter:3"
                        ],
                        "item_count": 1
                    }
                ]
            },
            {
                "name": "Dunes Wreck West \n (x: -1626, y: -357, z: 99)",
                "map_locations": 
                [
                    {
                        "map": "Crater",
                        "x": 78,
                        "y": 379
                    }
                ],
                "sections": 
                [
                    {
                        "name": "Databox",
                        "access_rules": 
                        [
                            "seaglide:2, rebreather",
                            "hightank, fins, rebreather, modify:3",
                            "vehiclebay:3, seamoth:3, rebreather",
                            "vehiclebay:3, prawn:4",
                            "vehiclebay:3, cyclops:9"
                        ],
                        "item_count": 1
                    }
                ]
            },
            {
                "name": "Dunes East Wreck \n (x: -1196, y: -223 z: 12)",
                "map_locations": 
                [
                    {
                        "map": "Crater",
                        "x": 173,
                        "y": 410
                    }
                ],
                "sections": 
                [
                    {
                        "name": "Outside Databox",
                        "access_rules": 
                        [
                            "seaglide:2, rebreather",
                            "hightank, fins, rebreather, modify:3",
                            "vehiclebay:3, seamoth:3, rebreather",
                            "vehiclebay:3, prawn:4",
                            "vehiclebay:3, cyclops:9"
                        ],
                        "item_count": 1
                    },
                    {
                        "name": "Inside Databox",
                        "access_rules": 
                        [
                            "seaglide:2, rebreather",
                            "hightank, fins, rebreather, modify:3",
                            "vehiclebay:3, seamoth:3, rebreather",
                            "vehiclebay:3, prawn:4",
                            "vehiclebay:3, cyclops:9"
                        ],
                        "item_count": 1
                    }
                ]
            },
            {
                "name": "Grand Reef North Wreck \n (x: -269, y: -262, z: -764)",
                "map_locations": 
                [
                    {
                        "map": "Crater",
                        "x": 363,
                        "y": 575
                    }
                ],
                "sections": 
                [
                    {
                        "name": "Outside Databox",
                        "access_rules": 
                        [
                            "seaglide:2, rebreather",
                            "hightank, fins, rebreather, modify:3",
                            "vehiclebay:3, seamoth:3, rebreather, cutter:3",
                            "vehiclebay:3, prawn:4",
                            "vehiclebay:3, cyclops:9"
                        ],
                        "item_count": 1
                    },
                    {
                        "name": "Elevator Databox",
                        "access_rules": 
                        [
                            "seaglide:2, rebreather, cutter:3",
                            "hightank, fins, rebreather, modify:3 cutter:3",
                            "vehiclebay:3, seamoth:3, rebreather, cutter:3",
                            "vehiclebay:3, prawn:4, cutter:3",
                            "vehiclebay:3, cyclops:9, cutter:3"
                        ],
                        "item_count": 1
                    },
                    {
                        "name": "Bottom Databox",
                        "access_rules": 
                        [
                            "seaglide:2, rebreather",
                            "hightank, fins, rebreather, modify:3",
                            "vehiclebay:3, seamoth:3, rebreather",
                            "vehiclebay:3, prawn:4",
                            "vehiclebay:3, cyclops:9"
                        ],
                        "item_count": 1
                    },
                    {
                        "name": "Hangar PDA",
                        "access_rules": 
                        [
                            "seaglide:2, rebreather",
                            "hightank, fins, rebreather, modify:3",
                            "vehiclebay:3, seamoth:3, rebreather",
                            "vehiclebay:3, prawn:4",
                            "vehiclebay:3, cyclops:9"
                        ],
                        "item_count": 1
                    }
                ]
            },
            {
                "name": "Grand Reef South Wreck \n (x: -850, y: -473, z: -1414)",
                "map_locations": 
                [
                    {
                        "map": "Crater",
                        "x": 250,
                        "y": 708
                    }
                ],
                "sections": 
                [
                    {
                        "name": "Trench Databox",
                        "access_rules": 
                        [
                            "seaglide:2, rebreather",
                            "hightank, fins, rebreather, modify:3",
                            "vehiclebay:3, seamoth:3, rebreather",
                            "vehiclebay:3, prawn:4",
                            "vehiclebay:3, cyclops:9"
                        ],
                        "item_count": 1
                    },
                    {
                        "name": "Comms Databox",
                        "access_rules": 
                        [
                            "seaglide:2, rebreather, cutter:3",
                            "hightank, fins, rebreather, modify:3, cutter:3",
                            "vehiclebay:3, seamoth:3, rebreather, cutter:3",
                            "vehiclebay:3, prawn:4, cutter:3",
                            "vehiclebay:3, cyclops:9, cutter:3"
                        ],
                        "item_count": 1
                    },
                    {
                        "name": "Outside Databox",
                        "access_rules": 
                        [   
                            "seaglide:2, rebreather",
                            "hightank, fins, rebreather, modify:3",
                            "vehiclebay:3, seamoth:3, rebreather",
                            "vehiclebay:3, prawn:4",
                            "vehiclebay:3, cyclops:9"
                        ],
                        "item_count": 1
                    },
                    {
                        "name": "PDA",
                        "access_rules": 
                        [
                            "seaglide:2, rebreather",
                            "hightank, fins, rebreather, modify:3",
                            "vehiclebay:3, seamoth:3, rebreather",
                            "vehiclebay:3, prawn:4",
                            "vehiclebay:3, cyclops:9"
                        ],
                        "item_count": 1
                    }
                ]
            },
            {
                "name": "Grassy Plateaus South Wreck \n (x: -23, y: -105, z: -604)",
                "map_locations": 
                [
                    {
                        "map": "Crater",
                        "x": 453,
                        "y": 548
                    }
                ],
                "sections": 
                [
                    {
                        "name": "Databox",
                        "access_rules": 
                        [
                            "rebreather, radsuit"
                        ],
                        "item_count": 1
                    },
                    {
                        "name": "PDA",
                        "access_rules": 
                        [
                            "rebreather, radsuit"
                        ],
                        "item_count": 1
                    }   
                ]
            },
            {
                "name": "Grassy Plateaus East Wreck \n (x: 313, y: -91, z: 432)",
                "map_locations": 
                [
                    {
                        "map": "Crater",
                        "x": 541,
                        "y": 299
                    }
                ],
                "sections": 
                [
                    {
                        "name": "Breach Databox",
                        "access_rules": 
                        [
                            "rebreather, cutter:3, radsuit"
                        ],  
                        "item_count": 1
                    },
                    {
                        "name": "Hangar Databox",
                        "access_rules":
                        [                         
                            "rebreather, cutter:3, radsuit"
                        ],
                        "item_count": 1
                    }
                ]
            },
            {
                "name": "Grassy Plateaus West Wreck \n (x: -632, y: -75, z: -8)",
                "map_locations": 
                [
                    {
                        "map": "Crater",
                        "x": 285,
                        "y": 405
                    }
                ],
                "sections": 
                [
                    {
                        "name": "Locker PDA",
                        "access_rules":
                        [
                            ""
                        ],
                        "item_count": 1
                    },
                    {
                        "name": "Beam PDA",
                        "access_rules":
                        [
                            ""
                        ],
                        "item_count": 1
                    },
                    {
                        "name": "Data Terminal",
                        "access_rules":
                        [
                            ""
                        ],
                        "item_count": 1
                    }
                ]
            },  
            {
                "name": "Grassy Plateaus South-West Wreck \n (x: -418, y: -94 z: -261)",
                "map_locations": 
                [
                    {
                        "map": "Crater",
                        "x": 342,
                        "y": 463
                    }
                ],
                "sections": 
                [
                    {
                        "name": "Databox",
                        "access_rules": 
                        [
                            "cutter:3"
                        ],
                        "item_count": 1
                    }
                ]
            },
            {
                "name": "Safe Shallows Wreck \n (x: -44, y: -29, z: -403)",
                "map_locations": 
                [
                    {
                        "map": "Crater",
                        "x": 423,
                        "y": 485
                    }
                ],
                "sections": 
                [
                    {
                        "name": "PDA",
                        "access_rules": 
                        [
                            ""
                        ],
                        "item_count": 1
                    }
                ]
            },
            {
                "name": "Kelp Forest West Wreck \n (x: -317, y: -79, z: 248)",
                "map_locations": 
                [
                    {
                        "map": "Crater",
                        "x": 365,
                        "y": 345
                    }
                ],
                "sections": 
                [
                    {
                        "name": "Databox",
                        "access_rules": 
                        [
                            ""
                        ],
                        "item_count": 1
                    }
                ]
            },
            {
                "name": "Kelp Forest North Wreck \n (x: 63, y: -38, z: 382)",
                "map_locations": 
                [
                    {
                        "map": "Crater",
                        "x": 459,
                        "y": 319
                    }
                ],
                "sections": 
                [
                    {
                        "name": "PDA",
                        "access_rules": 
                        [
                            ""
                        ],
                        "item_count": 1
                    }
                ]
            },
            {
                "name": "Mountains Central Wreck \n (x: 740, y: -346, z: 1220)",
                "map_locations": 
                [
                    {
                        "map": "Crater",
                        "x": 615,
                        "y": 138
                    }
                ],
                "sections": 
                [
                    {
                        "name": "Outside Databox",
                        "access_rules":
                        [
                            "seaglide:2, rebreather",
                            "hightank, fins, rebreather, modify:3",
                            "vehiclebay:3, seamoth:3, rebreather",
                            "vehiclebay:3, prawn:4",
                            "vehiclebay:3, cyclops:9"
                        ],
                        "item_count": 1
                    },
                    {
                        "name": "Office Databox",
                        "access_rules":
                        [
                            "seaglide:2, rebreather",
                            "hightank, fins, rebreather, modify:3",
                            "vehiclebay:3, seamoth:3, rebreather",
                            "vehiclebay:3, prawn:4",
                            "vehiclebay:3, cyclops:9"
                        ],
                        "item_count": 1
                    },
                    {
                        "name": "Hangar Databox",
                        "access_rules":
                        [
                            "seaglide:2, rebreather, cutter:3",
                            "hightank, fins, rebreather, modify:3, cutter:3",
                            "vehiclebay:3, seamoth:3, rebreather, cutter:3",
                            "vehiclebay:3, prawn:4, cutter:3",
                            "vehiclebay:3, cyclops:9, cutter:3"
                        ],
                        "item_count": 1
                    },
                    {
                        "name": "Data Terminal",
                        "access_rules":
                        [
                            "seaglide:2, rebreather, cutter:3",
                            "hightank, fins, rebreather, modify:3, cutter:3",
                            "vehiclebay:3, seamoth:3, rebreather, cutter:3",
                            "vehiclebay:3, prawn:4, cutter:3",
                            "vehiclebay:3, cyclops:9, cutter:3"
                        ],
                        "item_count": 1
                    }
                ]
            },
            {
                "name": "Mountains East Wreck \n (x: 1057, y: -254, z: 1359)",
                "map_locations": 
                [
                    {
                        "map": "Crater",
                        "x": 685,
                        "y": 110
                    }
                ],
                "sections": 
                [
                    {
                        "name": "Outside Databox",
                        "access_rules": 
                        [
                            "seaglide:2, rebreather",
                            "hightank, fins, rebreather, modify:3",
                            "vehiclebay:3, seamoth:3, rebreather",
                            "vehiclebay:3, prawn:4",
                            "vehiclebay:3, cyclops:9"
                        ],
                        "item_count": 1
                    },
                    {
                        "name": "Comms Databox",
                        "access_rules": 
                        [
                            "seaglide:2, rebreather",
                            "hightank, fins, rebreather, modify:3",
                            "vehiclebay:3, seamoth:3, rebreather",
                            "vehiclebay:3, prawn:4",
                            "vehiclebay:3, cyclops:9"
                        ],
                        "item_count": 1
                    }
                ]
            },  
            {
                "name": "Mushroom Forest Wreck \n (x: -672, y: -113, z: 750)",
                "map_locations": 
                [
                    {
                        "map": "Crater",
                        "x": 285,
                        "y": 225
                    }
                ],
                "sections": 
                [
                    {
                        "name": "Office Databox",
                        "access_rules": 
                        [
                            "rebreather"
                        ],
                        "item_count": 1
                    },
                    {
                        "name": "Cargo Databox",
                        "access_rules": 
                        [
                            "rebreather, cutter:3"
                        ],
                        "item_count": 1
                    },
                    {   
                        "name": "PDA",
                        "access_rules": 
                        [
                            "rebreather"
                        ],
                        "item_count": 1
                    }
                ]
            },
            {
                "name": "Sea Treader's Path Wreck \n (x: -1148, y: -166, z: -706)",
                "map_locations": 
                [
                    {
                        "map": "Crater",
                        "x": 180,
                        "y": 572
                    }
                ],
                "sections": 
                [
                    {
                        "name": "Outside Databox",
                        "access_rules": 
                        [
                            "seaglide:2, rebreather",
                            "hightank, fins, rebreather, modify:3",
                            "vehiclebay:3, seamoth:3, rebreather",
                            "vehiclebay:3, prawn:4",
                            "vehiclebay:3, cyclops:9"
                        ],
                        "item_count": 1
                    },
                    {
                        "name": "Lobby Databox",
                        "access_rules": 
                        [
                            "seaglide:2, rebreather, cutter:3",
                            "hightank, fins, rebreather, modify:3, cutter:3",
                            "vehiclebay:3, seamoth:3, rebreather, cutter:3",
                            "vehiclebay:3, prawn:4, cutter:3",
                            "vehiclebay:3, cyclops:9, cutter:3"
                        ],
                        "item_count": 1
                    },
                    {
                        "name": "Hangar Databox",
                        "access_rules": 
                        [
                            "rebreather"
                        ],
                        "item_count": 1
                    },
                    {
                        "name": "PDA",
                        "access_rules": 
                        [
                            "rebreather"
                        ],
                        "item_count": 1
                    }
                ]
            },
            {
                "name": "Sparse Reef Wreck \n (x: -781, y: -216, z: -730)",
                "map_locations": 
                [
                    {
                        "map": "Crater",
                        "x": 255,
                        "y": 570
                    }
                ],
                "sections": 
                [
                    {
                        "name": "Outside Databox",
                        "access_rules": 
                        [
                            "seaglide:2, rebreather",
                            "hightank, fins, rebreather, modify:3",
                            "vehiclebay:3, seamoth:3, rebreather",
                            "vehiclebay:3, prawn:4",
                            "vehiclebay:3, cyclops:9"
                        ],
                        "item_count": 1
                    },
                    {
                        "name": "Locker Databox",
                        "access_rules": 
                        [
                            "seaglide:2, rebreather , cutter:3",
                            "hightank, fins, rebreather, modify:3, cutter:3",
                            "vehiclebay:3, seamoth:3, rebreather, cutter:3",
                            "vehiclebay:3, prawn:4, cutter:3",
                            "vehiclebay:3, cyclops:9, cutter:3"
                        ],
                        "item_count": 1
                    },  
                    {
                        "name": "Lab Databox",
                        "access_rules": 
                        [
                            "seaglide:2, rebreather, cutter:3",
                            "hightank, fins, rebreather, modify:3, cutter:3",
                            "vehiclebay:3, seamoth:3, rebreather, cutter:3",
                            "vehiclebay:3, prawn:4, cutter:3",
                            "vehiclebay:3, cyclops:9, cutter:3"
                        ],
                        "item_count": 1
                    }
                ]
            },
            {
                "name": "Underwater Islands Wreck \n (x: -62, y: -192, z: 862)",
                "map_locations": 
                [
                    {
                        "map": "Crater",
                        "x": 428,
                        "y": 210
                    }
                ],
                "sections": 
                [
                    {
                        "name": "Outside Databox",
                        "access_rules": 
                        [
                            "rebreather"
                        ],
                        "item_count": 1
                    },
                    {
                        "name": "Hangar Databox",
                        "access_rules": 
                        [
                            "rebreather, cutter:3"
                        ],
                        "item_count": 1
                    },
                    {
                        "name": "Cable Databox",
                        "access_rules": 
                        [
                            "rebreather, cutter:3"
                        ],
                        "item_count": 1
                    },
                    {
                        "name": "Pipes Databox 1",
                        "access_rules": 
                        [
                            "rebreather, cannon:2"
                        ],
                        "item_count": 1
                    },
                    {
                        "name": "Pipes Databox 2",
                        "access_rules": 
                        [
                            "rebreather, cannon:2"
                        ],
                        "item_count": 1
                    },
                    {
                        "name": "Data Terminal",
                        "access_rules": 
                        [
                            "rebreather, cutter:3"
                        ],
                        "item_count": 1
                    }
                ]
            },
            {
                "name": "Deep Grand Reef Seabase \n (x: -630, y: -500, z: -930)",
                "map_locations": 
                [
                    {
                        "map": "Crater",
                        "x": 310,
                        "y": 640
                    }
                ],
                "sections": 
                [
                    {
                        "name": "Databox",
                        "access_rules": 
                        [
                            "seaglide:2, hightank, fins, rebreather, modify:3",
                            "vehiclebay:3, seamoth:3, rebreather, moonpool:2, smd1",
                            "vehiclebay:3, prawn:4",
                            "vehiclebay:3, cyclops:9"
                        ],
                        "item_count": 1
                    },
                    {
                        "name": "PDA",
                        "access_rules": 
                        [
                            "hightank, fins, rebreather, modify:3",
                            "vehiclebay:3, seamoth:3, rebreather, seaglide:2",
                            "vehiclebay:3, prawn:4",
                            "vehiclebay:3, cyclops:9"
                        ],
                        "item_count": 4
                    }
                ]
            },
            {
                "name": "Floating Island Central Base",
                "map_locations": 
                [
                    {
                        "map": "Crater",
                        "x": 265,
                        "y": 665
                    }
                ],
                "sections": 
                [
                    {
                        "name": "Databox",
                        "access_rules": 
                        [
                            ""
                        ],
                        "item_count": 1
                    },
                    {
                        "name": "PDA",
                        "access_rules": 
                        [
                            ""
                        ],
                        "item_count": 3
                    }
                ]
            },
            {
                "name": "Floating Island East Base",
                "map_locations": 
                [
                    {
                        "map": "Crater",
                        "x": 285,
                        "y": 690
                    }
                ],
                "sections": 
                [
                    {
                        "name": "PDA",
                        "access_rules": 
                        [
                            ""
                        ],
                        "item_count": 1
                    }
                ]
            },
            {
                "name": "Floating Island West Base",
                "map_locations": 
                [
                    {
                        "map": "Crater",
                        "x": 240,
                        "y": 650
                    }
                ],
                "sections": 
                [
                    {
                        "name": "PDA",
                        "access_rules": 
                        [
                            ""
                        ],
                        "item_count": 1
                    }
                ]   
            },
            {   
                "name": "Floating Island Cave Path",
                "map_locations": 
                [
                    {
                        "map": "Crater",
                        "x": 265,
                        "y": 690
                    }
                ],
                "sections": 
                [
                    {
                        "name": "PDA",
                        "access_rules": 
                        [
                            ""
                        ],
                        "item_count": 1
                    }
                ]
            },
            {
                "name": "Floating Island Rendevous Point",
                "map_locations": 
                [
                    {
                        "map": "Crater",
                        "x": 280,
                        "y": 657
                    }
                ],
                "sections": 
                [
                    {
                        "name": "PDA",
                        "access_rules": 
                        [
                            ""
                        ],
                        "item_count": 1
                    }
                ]
            },
            {
                "name": "Lifepod 2 \n (x: -481.4, y: -503.6, z: 1324)",
                "map_locations": 
                [
                    {
                        "map": "Crater",
                        "x": 337,
                        "y": 120
                    }
                ],  
                "sections": 
                [
                    {
                        "name": "Databox",
                        "access_rules": 
                        [
                            "hightank, fins, rebreather, modify:3",
                            "vehiclebay:3, seamoth:3, rebreather, seaglide:2",
                            "vehiclebay:3, prawn:4",
                            "vehiclebay:3, cyclops:9"
                        ],
                        "item_count": 1
                    },
                    {
                        "name": "PDA",
                        "access_rules": 
                        [
                            "hightank, fins, rebreather, modify:3",
                            "vehiclebay:3, seamoth:3, rebreather, seaglide:2",
                            "vehiclebay:3, prawn:4",
                            "vehiclebay:3, cyclops:9"
                        ],
                        "item_count": 1
                    }
                ]
            },
            {
                "name": "Lifepod 3 \n (x: -26, y: -18, z: 414)",
                "map_locations": 
                [
                    {
                        "map": "Crater",
                        "x": 435,
                        "y": 315
                    }
                ],
                "sections": 
                [
                    {
                        "name": "Databox",
                        "access_rules": 
                        [
                            ""
                        ],
                        "item_count": 1
                    },
                    {
                        "name": "PDA",
                        "access_rules": 
                        [
                            ""
                        ],
                        "item_count": 1
                    }
                ]
            },
            {
                "name": "Lifepod 4 \n (x: 710, y: -5, z: 152)",
                "map_locations": 
                [
                    {
                        "map": "Crater",
                        "x": 555,
                        "y": 415
                    }
                ],
                "sections": 
                [
                    {
                        "name": "Databox",
                        "access_rules": 
                        [
                            "radsuit"
                        ],
                        "item_count": 1
                    },
                    {
                        "name": "PDA",
                        "access_rules": 
                        [
                            "radsuit"
                        ],
                        "item_count": 1
                    }
                ]
            },
            {
                "name": "Lifepod 6 \n (x: 356, Y: -109, z: 312)",
                "map_locations": 
                [
                    {
                        "map": "Crater",
                        "x": 538,
                        "y": 340
                    }
                ],
                "sections": 
                [
                    {
                        "name": "Databox",
                        "access_rules": 
                        [
                            "radsuit"
                        ],
                        "item_count": 1
                    },
                    {
                        "name": "Inside PDA",
                        "access_rules": 
                        [
                            "radsuit"
                        ],
                        "item_count": 1
                    },
                    {   
                        "name": "Outside PDA",
                        "access_rules": 
                        [
                            "radsuit"
                        ],
                        "item_count": 1
                    }
                ]
            },
            {
                "name": "Lifepod 7 \n (x: -55, Y: -179, X: -1039)",
                "map_locations": 
                [
                    {
                        "map": "Crater",
                        "x": 430,
                        "y": 648
                    }
                ],  
                "sections": 
                [
                    {
                        "name": "PDA",
                        "access_rules": 
                        [
                            "rebreather"
                        ],
                        "item_count": 1
                    }
                ]
            },
            {
                "name": "Lifepod 13 \n (x: -922, y: -177, z: 501)",
                "map_locations": 
                [
                    {
                        "map": "Crater",
                        "x": 235,
                        "y": 287
                    }
                ],
                "sections": 
                [
                    {
                        "name": "Databox",
                        "access_rules": 
                        [
                            "rebreather"
                        ],
                        "item_count": 1
                    },
                    {
                        "name": "PDA",
                        "access_rules": 
                        [
                            "rebreather"
                        ],
                        "item_count": 1
                    }   
                ]
            },
            {
                "name": "Lifepod 17 \n (x: -515, y: -91, z: -56)",
                "map_locations": 
                [
                    {
                        "map": "Crater",
                        "x": 320,
                        "y": 415
                    }
                ],
                "sections": 
                [
                    {
                        "name": "PDA",
                        "access_rules": 
                        [
                            ""
                        ],
                        "item_count": 1
                    }
                ]
            },
            {
                "name": "Lifepod 19 \n (x: -806, y: -297, z: -882)",
                "map_locations": 
                [
                    {
                        "map": "Crater",
                        "x": 245,
                        "y": 610
                    }
                ],
                "sections": 
                [
                    {
                        "name": "Databox",
                        "access_rules": 
                        [
                            "seaglide:2, rebreather",
                            "hightank, fins, rebreather, modify:3",
                            "vehiclebay:3, seamoth:3, rebreather",
                            "vehiclebay:3, prawn:4",
                            "vehiclebay:3, cyclops:9"
                        ],
                        "item_count": 1
                    },
                    {
                        "name": "Outside PDA",
                        "access_rules": 
                        [
                            "seaglide:2, rebreather",
                            "hightank, fins, rebreather, modify:3",
                            "vehiclebay:3, seamoth:3, rebreather",
                            "vehiclebay:3, prawn:4",
                            "vehiclebay:3, cyclops:9"
                        ],
                        "item_count": 1
                    },
                    {
                        "name": "Inside PDA",
                        "access_rules": 
                        [
                            "seaglide:2, rebreather",
                            "hightank, fins, rebreather, modify:3",
                            "vehiclebay:3, seamoth:3, rebreather",
                            "vehiclebay:3, prawn:4",
                            "vehiclebay:3, cyclops:9"
                        ],
                        "item_count": 1
                    }
                ]
            },
            {
                "name": "Aurora Seamoth Bay",
                "map_locations": 
                [
                    {
                        "map": "Crater",
                        "x": 642,
                        "y": 428
                    }
                ],
                "sections": 
                [
                    {
                        "name": "Upgrade Console",
                        "access_rules": 
                        [
                            "repair, radsuit"
                        ],
                        "item_count": 1
                    },
                    {
                        "name": "PDA",
                        "access_rules": 
                        [
                            "repair, radsuit"
                        ],
                        "item_count": 1
                    }
                ]
            },
            {
                "name": "Aurora Drive Core",
                "map_locations": 
                [
                    {
                        "map": "Crater",
                        "x": 625,
                        "y": 440
                    }
                ],
                "sections": 
                [
                    {
                        "name": "Upgrade Console",
                        "access_rules": 
                        [
                            "radsuit"
                        ],
                        "item_count": 1
                    }
                ]
            },
            {
                "name": "Aurora PRAWN Bay",
                "map_locations": 
                [
                    {
                        "map": "Crater",
                        "x": 665,
                        "y": 440
                    }
                ],
                "sections": 
                [
                    {
                        "name": "Upgrade Console",
                        "access_rules": 
                        [
                            "cutter:3, radsuit"
                        ],
                        "item_count": 1
                    }
                ]   
            },
            {
                "name": "Aurora Lab",
                "map_locations": 
                [
                    {
                        "map": "Crater",
                        "x": 675,
                        "y": 420
                    }
                ],
                "sections": 
                [
                    {
                        "name": "Outside Lab PDA",
                        "access_rules": 
                        [
                            "radsuit, cannon:2",
                            "radsuit, cutter:3"
                        ],
                        "item_count": 1
                    },
                    {   
                        "name": "Inside Lab PDA \n (Code 6483)",
                        "access_rules": 
                        [
                            "radsuit, cannon:2",
                            "radsuit, cutter:3"
                        ],
                        "item_count": 1
                    },
                    {   
                        "name": "Inside Lab Upgrade Console \n (Code 6483)",
                        "access_rules": 
                        [
                            "radsuit, cannon:2",
                            "radsuit, cutter:3"
                        ],
                        "item_count": 1
                    }
                ]
            },
            {
                "name": "Aurora Entrance Bay",
                "map_locations": 
                [
                    {
                        "map": "Crater",
                        "x": 660,
                        "y": 425
                    }
                ],
                "sections": 
                [
                    {
                        "name": "Aurora Office PDA",
                        "access_rules": 
                        [
                            "radsuit"
                        ],
                        "item_count": 1
                    },
                    {
                        "name": "Aurora Office Upgrade Console",
                        "access_rules": 
                        [
                            "radsuit"
                        ],
                        "item_count": 1
                    },
                    {
                        "name": "Outside Cargo Bay PDA",
                        "access_rules": 
                        [
                            "radsuit"
                        ],
                        "item_count": 1
                    },
                    {
                        "name": "Cargo Bay PDA \n (Code 1454)",
                        "access_rules": 
                        [
                            "radsuit"
                        ],
                        "item_count": 1
                    }
                ]
            },
            {
                "name": "Aurora Crew Quarters",
                "map_locations": 
                [
                    {
                        "map": "Crater",
                        "x": 650,
                        "y": 465
                    }
                ],
                "sections": 
                [
                    {
                        "name": "Cafeteria PDA",
                        "access_rules": 
                        [
                            "radsuit, cutter:3, repair",
                            "radsuit, cutter:3, cannon:2"
                        ],
                        "item_count": 1
                    },  
                    {
                        "name": "Cabin 1 PDA \n (Code 1869)",
                        "access_rules": 
                        [
                            "radsuit, cutter:3, repair",
                            "radsuit, cutter:3, cannon:2"
                        ],
                        "item_count": 1
                    },
                    {
                        "name": "Cabin 4 PDA",
                        "access_rules": 
                        [
                            "radsuit, cutter:3 ,repair",
                            "radsuit, cutter:3, cannon:2"
                        ],
                        "item_count": 1
                    },
                    {
                        "name": "Cabin 7 PDA",
                        "access_rules": 
                        [
                            "radsuit, cutter:3, repair",
                            "radsuit, cutter:3, cannon:2"
                        ],
                        "item_count": 1
                    },
                    {
                        "name": "Captain's Quarters PDA \n (Code 2679)",
                        "access_rules": 
                        [
                            "radsuit, cutter:3, repair",
                            "radsuit, cutter:3, cannon:2"
                        ],
                        "item_count": 1
                    },
                    {
                        "name": "Captain's Quarters Data Terminal \n (Code 2679)",
                        "access_rules": 
                        [
                            "radsuit, cutter:3, repair",
                            "radsuit, cutter:3, cannon:2"
                        ],
                        "item_count": 1
                    }
                ]
            },  
            {
                "name": "Aurora Locker Room",
                "map_locations": 
                [
                    {
                        "map": "Crater",
                        "x": 645,
                        "y": 449
                    }
                ],
                "sections": 
                [
                    {
                        "name": "PDA",
                        "access_rules": 
                        [
                            "radsuit, cutter:3, repair"
                        ],
                        "item_count": 1
                    },
                    {
                        "name": "Medkit PDA",
                        "access_rules": 
                        [
                            "radsuit, cutter:3, repair"
                        ],
                        "item_count": 1
                    }
                ]
            },
            {
                "name": "Aurora Black Box",
                "map_locations": 
                [
                    {
                        "map": "Crater",
                        "x": 685,
                        "y": 435
                    }
                ],
                "sections": 
                [
                    {
                        "name": "Data Terminal",
                        "access_rules": 
                        [
                            "radsuit, cutter:3, repair",
                            "radsuit, cutter:3, cannon:2"
                        ],
                        "item_count": 1
                    }
                ]
            },
            {
                "name": "Quarantine Enforcement Platform",
                "map_locations": 
                [
                    {
                        "map": "Crater",
                        "x": 535,
                        "y": 210
                    }
                ],
                "sections": 
                [
                    {
                        "name": "Upper Alien Terminal",
                        "access_rules": 
                        [
                            ""
                        ],
                        "item_count": 1
                    },
                    {
                        "name": "Center Alien Terminal",
                        "access_rules": 
                        [
                            ""
                        ],
                        "item_count": 1
                    }
                ]
            },
            {
                "name": "Dunes Sanctuary \n (x: -1256, y: -398, z: 1097)",
                "map_locations": 
                [
                    {
                        "map": "Crater",
                        "x": 182,
                        "y": 173
                    }
                ],
                "sections": 
                [
                    {
                        "name": "Alien Terminal \n (Requires Purple Tablet)",
                        "access_rules": 
                        [
                            "seaglide:2, rebreather",
                            "hightank, fins, rebreather, modify:3",
                            "seamoth:3, vehiclebay:3, rebreather",
                            "vehiclebay:3, prawn:4",
                            "vehiclebay:3, cyclops:9"
                        ],
                        "item_count": 1
                    }
                ]
            },
            {
                "name": "Sparse Reef Sanctuary \n (x: -884, y: -308, z: -792)",
                "map_locations": 
                [
                    {
                        "map": "Crater",
                        "x": 230,
                        "y": 600
                    }
                ],
                "sections": 
                [
                    {
                        "name": "Alien Terminal \n (Requires Purple Tablet)",
                        "access_rules": 
                        [
                            "seaglide:2, rebreather",
                            "hightank, fins, rebreather, modify:3",
                            "seamoth:3, vehiclebay:3, rebreather",
                            "vehiclebay:3, prawn:4",
                            "vehiclebay:3, cyclops:9"
                        ],
                        "item_count": 1
                    }
                ]
            },
            {
                "name": "North Blood Kelp Sanctuary \n (x: -601, y: -558, z: 1485)",
                "map_locations": 
                [
                    {
                        "map": "Crater",
                        "x": 315,
                        "y": 82
                    }
                ],
                "sections": 
                [
                    {
                        "name": "Alien Terminal \n (Requires Purple Tablet)",
                        "access_rules": 
                        [
                            "hightank, fins, rebreather, modify:3, seaglide:2",
                            "vehiclebay:3, seamoth:3, rebreather, seaglide:2",
                            "vehiclebay:3, prawn:4",
                            "vehiclebay:3, cyclops:9"
                        ],
                        "item_count": 1
                    }
                ]
            }
        ]
    }
]   